injecty/__init__.py
injecty/injecty_context.py
injecty-0.0.9.dist-info/METADATA
injecty-0.0.9.dist-info/WHEEL
injecty-0.0.9.dist-info/RECORD
