Metadata-Version: 2.4
Name: injecty
Version: 0.0.9
Summary: A simple IOC / Dependency injection micro framework for Python.
Project-URL: Repository, https://github.com/tofarr/servey-stub
Author-email: Tim O'Farrell <tofarr@gmail.com>
License: MIT
Classifier: License :: OSI Approved :: MIT License
Classifier: Operating System :: OS Independent
Classifier: Programming Language :: Python :: 3
Requires-Python: >=3.10
Provides-Extra: dev
Requires-Dist: black>=23.3; extra == 'dev'
Requires-Dist: pylint>=3.0; extra == 'dev'
Requires-Dist: pytest-cov>=4.0; extra == 'dev'
Requires-Dist: pytest-xdist>=3.2; extra == 'dev'
Requires-Dist: pytest>=7.2; extra == 'dev'
